mediastack/__init__.py
mediastack/const.py
mediastack/core.py
mediastack/errors.py
mediastack/utils.py
py_mediastack-0.1.1.dist-info/LICENSE
py_mediastack-0.1.1.dist-info/METADATA
py_mediastack-0.1.1.dist-info/WHEEL
py_mediastack-0.1.1.dist-info/top_level.txt
py_mediastack-0.1.1.dist-info/RECORD
