Metadata-Version: 2.1
Name: py-mediastack
Version: 0.1.1
Summary: An unofficial python helper package to interact with the mediastack API.
Home-page: https://github.com/Adwaith-Rajesh/py-mediastack
Author: Adwaith Rajesh
Author-email: adwaithrajesh3180@gmail.com
License: MIT
Platform: UNKNOWN
Classifier: License :: OSI Approved :: MIT License
Classifier: Programming Language :: Python :: 3
Classifier: Programming Language :: Python :: 3 :: Only
Classifier: Programming Language :: Python :: 3.6
Classifier: Programming Language :: Python :: 3.7
Classifier: Programming Language :: Python :: 3.8
Classifier: Programming Language :: Python :: 3.9
Requires-Python: >=3.6.1
Requires-Dist: requests
